configurenv.py
configurenv-1.0.0.dist-info/licenses/LICENSE
configurenv-1.0.0.dist-info/METADATA
configurenv-1.0.0.dist-info/WHEEL
configurenv-1.0.0.dist-info/top_level.txt
configurenv-1.0.0.dist-info/RECORD
