Metadata-Version: 2.4
Name: configurenv
Version: 1.0.0
Author-email: Peter Eichman <peichman@umd.edu>
Maintainer-email: UMD Libraries <lib-ssdr@umd.edu>
License-Expression: Apache-2.0
Project-URL: Repository, https://github.com/umd-lib/configurenv
Classifier: Development Status :: 5 - Production/Stable
Classifier: Programming Language :: Python :: 3 :: Only
Classifier: Operating System :: OS Independent
Requires-Python: >=3.10
License-File: LICENSE
Requires-Dist: pyyaml
Provides-Extra: test
Requires-Dist: pytest; extra == "test"
Requires-Dist: pytest-datadir; extra == "test"
Requires-Dist: pytest-cov; extra == "test"
Requires-Dist: ruff; extra == "test"
Dynamic: license-file
